Metadata-Version: 2.1
Name: create-fast-app
Version: 0.0.2
Summary: A small package to bootstrap a fast api application
Author-email: Nedu Ekeruche <cekeruche@icloud.com>
Project-URL: Homepage, https://github.com/Chinedu-E/create_fast_app
Classifier: Programming Language :: Python :: 3
Classifier: License :: OSI Approved :: MIT License
Classifier: Operating System :: OS Independent
Requires-Python: >=3.7
License-File: LICENSE
Requires-Dist: click (>=8.0)
